[
    {
        "weeklyRank": 1,
        "cumulativeWeeksInTop10": 7,
        "maturityRating": "TV-PG",
        "weeklyHoursViewed": 37850000,
        "weeklyViews": 0,
        "runtime": "0",
        "runtime_second": 0,
        "runtime_hmm": "0:00",
        "bigImage": "https://dnm.nflximg.net/api/v6/E8vDc_W8CLv7-yMQu8KMEC7Rrr8/AAAABbYPZNxcOyOo6SYwxyf51IF4mjfl1m30ceiL5DDttVsWg5RfTik0xtrPP6SPIpyjTCn479WudV1QkrM_3GIM9czDtvX1rm3rU4Bt.jpg?r=26d",
        "weekEndDate": "2022-11-20",
        "videoId": "81416312",
        "category": "ENGLISH_MOVIES",
        "title": "Falling for Christmas",
        "shortSynopsis": "After losing her memory in a skiing accident, a spoiled heiress lands in the cozy care of a down-on-his-luck widower and his daughter at Christmastime.",
        "releaseYear": "2022",
        "groupfile": "films"
    },
    {
        "weeklyRank": 2,
        "cumulativeWeeksInTop10": 4,
        "maturityRating": "PG",
        "weeklyHoursViewed": 33370000,
        "weeklyViews": 0,
        "runtime": "0",
        "runtime_second": 0,
        "runtime_hmm": "0:00",
        "bigImage": "https://dnm.nflximg.net/api/v6/E8vDc_W8CLv7-yMQu8KMEC7Rrr8/AAAABZ9jzIqX63CS25KaEbcjtSHVkHAdPOExTuiX1YZ5bE-PLDHmJVYnP9DrneVdXnCK_uyY533mLfDLySx5NkpX7SkzNCsb1LF7_ACo.jpg?r=e18",
        "weekEndDate": "2022-11-20",
        "videoId": "81220825",
        "category": "ENGLISH_MOVIES",
        "title": "Slumberland",
        "shortSynopsis": "Joined by a larger-than-life outlaw, a daring young orphan journeys through a land of dreams to find a precious pearl that will grant her greatest wish.",
        "releaseYear": "2022",
        "groupfile": "films"
    },
    {
        "weeklyRank": 3,
        "cumulativeWeeksInTop10": 2,
        "maturityRating": "R",
        "weeklyHoursViewed": 26180000,
        "weeklyViews": 0,
        "runtime": "0",
        "runtime_second": 0,
        "runtime_hmm": "0:00",
        "bigImage": "https://dnm.nflximg.net/api/v6/E8vDc_W8CLv7-yMQu8KMEC7Rrr8/AAAABZYKeO7bPraim95Z5PiPzd2bvoWFmAuObLIRpiGIsY352zVuYBsSOnH03SMi35VnHbCygmPO2xIkI56Tcyx9Mv9cA06ShTVpSmAv.jpg?r=e6b",
        "weekEndDate": "2022-11-20",
        "videoId": "81426931",
        "category": "ENGLISH_MOVIES",
        "title": "The Wonder",
        "shortSynopsis": "Haunted by her past, a nurse travels from England to a remote Irish village in 1862 to investigate a young girl's supposedly miraculous fast.",
        "releaseYear": "2022",
        "groupfile": "films"
    },
    {
        "weeklyRank": 4,
        "cumulativeWeeksInTop10": 4,
        "maturityRating": "PG-13",
        "weeklyHoursViewed": 21420000,
        "weeklyViews": 0,
        "runtime": "0",
        "runtime_second": 0,
        "runtime_hmm": "0:00",
        "bigImage": "https://dnm.nflximg.net/api/v6/E8vDc_W8CLv7-yMQu8KMEC7Rrr8/AAAABVJtskW_OtOAw9ydfuDXh5zxL8TmzbNxDqDpEj7nCckWeABerEnGrkj1lUB1Jl8HEj0fc0qdTYrOzdBAKwlxNB_ztyBm6o0lo7TD.jpg?r=67e",
        "weekEndDate": "2022-11-20",
        "videoId": "81406219",
        "category": "ENGLISH_MOVIES",
        "title": "Enola Holmes 2",
        "shortSynopsis": "Enola takes on her first official case as a detective, but to solve the mystery of a missing girl, she'll need help from friends — and brother Sherlock.",
        "releaseYear": "2022",
        "groupfile": "films"
    },
    {
        "weeklyRank": 5,
        "cumulativeWeeksInTop10": 5,
        "maturityRating": "PG-13",
        "weeklyHoursViewed": 20330000,
        "weeklyViews": 0,
        "runtime": "0",
        "runtime_second": 0,
        "runtime_hmm": "0:00",
        "bigImage": "https://dnm.nflximg.net/api/v6/E8vDc_W8CLv7-yMQu8KMEC7Rrr8/AAAABWb2bCHQ_KoQ6XtHFzwq3tR1X-2PBzG82RDC3uIT63TCHmuSRDp_TfHYpdjDMVUfebZX7FHGM3C-3nSGv-26N5PeVBDpYYUl9nKt.jpg?r=6cf",
        "weekEndDate": "2022-11-20",
        "videoId": "81564396",
        "category": "ENGLISH_MOVIES",
        "title": "Where the Crawdads Sing",
        "shortSynopsis": "A woman who grew up alone in the wild North Carolina marshes becomes a suspect in the murder of a well-to-do young man from the nearby town.",
        "releaseYear": "2022",
        "groupfile": "films"
    },
    {
        "weeklyRank": 6,
        "cumulativeWeeksInTop10": 2,
        "maturityRating": "TV-PG",
        "weeklyHoursViewed": 17930000,
        "weeklyViews": 0,
        "runtime": "0",
        "runtime_second": 0,
        "runtime_hmm": "0:00",
        "bigImage": "https://dnm.nflximg.net/api/v6/E8vDc_W8CLv7-yMQu8KMEC7Rrr8/AAAABWoHeZvoTfUYH57HTxPfUvbQkb3RzdTBECUqQyBB0rM2YjOOnq9PKRRGDjboYhwEUWJTNk-LwC9vnHixu4yhAoZT1CiTA-ej89kA.jpg?r=8ac",
        "weekEndDate": "2022-11-20",
        "videoId": "81304917",
        "category": "ENGLISH_MOVIES",
        "title": "Christmas with You",
        "shortSynopsis": "Seeking inspiration for a hit holiday song, a pop star grants a young fan's Christmas wish to meet her — and finds a shot at true love along the way.",
        "releaseYear": "2022",
        "groupfile": "films"
    },
    {
        "weeklyRank": 7,
        "cumulativeWeeksInTop10": 2,
        "maturityRating": "TV-Y7",
        "weeklyHoursViewed": 10500000,
        "weeklyViews": 0,
        "runtime": "0",
        "runtime_second": 0,
        "runtime_hmm": "0:00",
        "bigImage": "https://dnm.nflximg.net/api/v6/E8vDc_W8CLv7-yMQu8KMEC7Rrr8/AAAABUFWoN0JmNQr21HO2t13CUzkUI--0cYPxRdmbTjfBalmMnVzGs8UOtl0IEjB86oHnyMrufYZ49Ysbcl-kEtT9IhP8qtroybym61j.jpg?r=222",
        "weekEndDate": "2022-11-20",
        "videoId": "81589565",
        "category": "ENGLISH_MOVIES",
        "title": "Minions & More Volume 2",
        "shortSynopsis": "Catch animated shorts like \"Phil’s Dance Party\" and \"Binky Nelson Unpacified\" in this compilation from the company behind the \"Despicable Me\" franchise.",
        "releaseYear": "2022",
        "groupfile": "films"
    },
    {
        "weeklyRank": 8,
        "cumulativeWeeksInTop10": 4,
        "maturityRating": "R",
        "weeklyHoursViewed": 8800000,
        "weeklyViews": 0,
        "runtime": "0",
        "runtime_second": 0,
        "runtime_hmm": "0:00",
        "bigImage": "https://dnm.nflximg.net/api/v6/E8vDc_W8CLv7-yMQu8KMEC7Rrr8/AAAABVdXjrkhMvkOxGmLX6Nhw1LGrU2KrI2SfuA42upz4bxx_y9NN64yn5X0Vzfr6sd1zEE_2KQ71BPeN7ThglcmeEVNvyt-0TyyxZwZ.jpg?r=ef9",
        "weekEndDate": "2022-11-20",
        "videoId": "81260083",
        "category": "ENGLISH_MOVIES",
        "title": "The Good Nurse",
        "shortSynopsis": "An overburdened ICU nurse leans on her selfless new colleague at work and at home — until a patient's unexpected death casts him in a suspicious light.",
        "releaseYear": "2022",
        "groupfile": "films"
    },
    {
        "weeklyRank": 9,
        "cumulativeWeeksInTop10": 3,
        "maturityRating": "PG-13",
        "weeklyHoursViewed": 7610000,
        "weeklyViews": 0,
        "runtime": "0",
        "runtime_second": 0,
        "runtime_hmm": "0:00",
        "bigImage": "https://dnm.nflximg.net/api/v6/E8vDc_W8CLv7-yMQu8KMEC7Rrr8/AAAABRsf0KxpySz9K7tXGXDoMxfPyJizdKXKKUeF9aQ_hSLs6XW6lk7eQFWnpQ1TqsF_Tg8ELbO_Yd8OFJ9YnzmCujFmP9AS-Nl9A7-f.jpg?r=ce4",
        "weekEndDate": "2022-11-20",
        "videoId": "81277950",
        "category": "ENGLISH_MOVIES",
        "title": "Enola Holmes",
        "shortSynopsis": "While searching for her missing mother, intrepid teen Enola Holmes uses her sleuthing skills to outsmart big brother Sherlock and help a runaway lord.",
        "releaseYear": "2020",
        "groupfile": "films"
    },
    {
        "weeklyRank": 10,
        "cumulativeWeeksInTop10": 1,
        "maturityRating": "TV-14",
        "weeklyHoursViewed": 7500000,
        "weeklyViews": 0,
        "runtime": "0",
        "runtime_second": 0,
        "runtime_hmm": "0:00",
        "bigImage": "https://dnm.nflximg.net/api/v6/E8vDc_W8CLv7-yMQu8KMEC7Rrr8/AAAABfE1FgKYD8Ol9r6c6NddsKdaIYWa7SygKSBOhpiE5IGtLK01xZ_-MZjGxrxLSYjPzdUsh5RpO9_hFoXHzS0uzwbxN4z9W6W2aY68.jpg?r=97c",
        "weekEndDate": "2022-11-20",
        "videoId": "81460514",
        "category": "ENGLISH_MOVIES",
        "title": "I Am Vanessa Guillen",
        "shortSynopsis": "Vanessa Guillen was 20 years old when she was found murdered at a US Army base. Rather than submit to silence, her family fought for justice and change.",
        "releaseYear": "2022",
        "groupfile": "films"
    },
    {
        "weeklyRank": 1,
        "cumulativeWeeksInTop10": 5,
        "maturityRating": "TV-MA",
        "weeklyHoursViewed": 18700000,
        "weeklyViews": 0,
        "runtime": "0",
        "runtime_second": 0,
        "runtime_hmm": "0:00",
        "bigImage": "https://dnm.nflximg.net/api/v6/E8vDc_W8CLv7-yMQu8KMEC7Rrr8/AAAABWzVDVIsoo7BNm-BjC_vOFx2Gc47e9ZFtFMI87MRW4KE9CJrJqlPLJlhoNMirskbyXzt7chCNLi9V8kR9PML_7_mb6cETE5OLDEb.jpg?r=9a5",
        "weekEndDate": "2022-11-20",
        "videoId": "81509213",
        "category": "NONENGLISH_MOVIES",
        "title": "Lost Bullet 2",
        "shortSynopsis": "Having cleared his name, genius mechanic Lino has only one goal in mind: getting revenge on the corrupt cops who killed his brother and his mentor.",
        "releaseYear": "2022",
        "groupfile": "films-non-english"
    },
    {
        "weeklyRank": 2,
        "cumulativeWeeksInTop10": 23,
        "maturityRating": "R",
        "weeklyHoursViewed": 9490000,
        "weeklyViews": 0,
        "runtime": "0",
        "runtime_second": 0,
        "runtime_hmm": "0:00",
        "bigImage": "https://dnm.nflximg.net/api/v6/E8vDc_W8CLv7-yMQu8KMEC7Rrr8/AAAABZy9EmEd_pZqnvcgfWPCWecKKt5WCRvMoQGMQtG0SSAeKuu5RCj5LOrHw4aFGxJjcMcpwIAUxDVJW5KIAiKZGqyiDtK3G9JhAUQf.jpg?r=e2e",
        "weekEndDate": "2022-11-20",
        "videoId": "81260280",
        "category": "NONENGLISH_MOVIES",
        "title": "All Quiet on the Western Front",
        "shortSynopsis": "When 17-year-old Paul joins the Western Front in World War I, his initial excitement is soon shattered by the grim reality of life in the trenches.",
        "releaseYear": "2022",
        "groupfile": "films-non-english"
    },
    {
        "weeklyRank": 3,
        "cumulativeWeeksInTop10": 10,
        "maturityRating": "TV-MA",
        "weeklyHoursViewed": 6870000,
        "weeklyViews": 0,
        "runtime": "0",
        "runtime_second": 0,
        "runtime_hmm": "0:00",
        "bigImage": "https://dnm.nflximg.net/api/v6/E8vDc_W8CLv7-yMQu8KMEC7Rrr8/AAAABQRv3zZHc0ISgkgG0kyJqyLlAVe7Y0ysYVDsgN6Yv5q6Qaoq_jNsnsgIMvrJ0E3MkDk14MLU738xPxaIj8DoVyfh6AoJ2mGqobic.jpg?r=81d",
        "weekEndDate": "2022-11-20",
        "videoId": "81108579",
        "category": "NONENGLISH_MOVIES",
        "title": "Lost Bullet",
        "shortSynopsis": "Facing a murder charge, a genius mechanic with a criminal past must track down a missing car containing the proof of his innocence: a single bullet.",
        "releaseYear": "2020",
        "groupfile": "films-non-english"
    },
    {
        "weeklyRank": 4,
        "cumulativeWeeksInTop10": 5,
        "maturityRating": "TV-MA",
        "weeklyHoursViewed": 6130000,
        "weeklyViews": 0,
        "runtime": "0",
        "runtime_second": 0,
        "runtime_hmm": "0:00",
        "bigImage": "https://dnm.nflximg.net/api/v6/E8vDc_W8CLv7-yMQu8KMEC7Rrr8/AAAABf_BNixrnaV3VrGO86WdhC65DNEu_QoXWVADyabwRbD8f9jmHWhWPjskUb2B65C0ESkBloafMkSjisx6uR72OPvCWyLK6pwGzhK2.jpg?r=cd7",
        "weekEndDate": "2022-11-20",
        "videoId": "81435930",
        "category": "NONENGLISH_MOVIES",
        "title": "Beyond the Universe",
        "shortSynopsis": "While waiting for a kidney transplant, a young pianist finds an unexpected connection with her doctor — and the courage to fulfill her musical dreams.",
        "releaseYear": "2022",
        "groupfile": "films-non-english"
    },
    {
        "weeklyRank": 5,
        "cumulativeWeeksInTop10": 2,
        "maturityRating": "TV-MA",
        "weeklyHoursViewed": 5840000,
        "weeklyViews": 0,
        "runtime": "0",
        "runtime_second": 0,
        "runtime_hmm": "0:00",
        "bigImage": "https://dnm.nflximg.net/api/v6/E8vDc_W8CLv7-yMQu8KMEC7Rrr8/AAAABXBihNEyMhQXbRNRh6xsuwfh4mVu_ZX3zn2v79tTSiyPPLHENM8XBGTxc_zLDF-QSWHp3lLDRwKAPrAVQ61NxC5rv9xKvPyGg7YC.jpg?r=7a9",
        "weekEndDate": "2022-11-20",
        "videoId": "81444027",
        "category": "NONENGLISH_MOVIES",
        "title": "Monica, O My Darling",
        "shortSynopsis": "A slick robotics expert joins a murderous plot after a passionate affair takes a sudden turn, but nothing — not even death — is what it seems to be.",
        "releaseYear": "2022",
        "groupfile": "films-non-english"
    },
    {
        "weeklyRank": 6,
        "cumulativeWeeksInTop10": 1,
        "maturityRating": "TV-MA",
        "weeklyHoursViewed": 4690000,
        "weeklyViews": 0,
        "runtime": "0",
        "runtime_second": 0,
        "runtime_hmm": "0:00",
        "bigImage": "https://dnm.nflximg.net/api/v6/E8vDc_W8CLv7-yMQu8KMEC7Rrr8/AAAABX3vYXVWEMn1bqWVPJRR8Lf_D5kbraztwKs8X4ls-M3sTDP1ZtdvRpHppsOu2riWz-4owN-Is7TQ4LSoHl8iphpn0Oir7YT9mcht.jpg?r=e05",
        "weekEndDate": "2022-11-20",
        "videoId": "81082516",
        "category": "NONENGLISH_MOVIES",
        "title": "Racionais MC's: From the Streets of São Paulo",
        "shortSynopsis": "With their music and a message, influential hip-hop group Racionais MC's turned their street poetry into a powerful movement in Brazil and beyond.",
        "releaseYear": "2022",
        "groupfile": "films-non-english"
    },
    {
        "weeklyRank": 7,
        "cumulativeWeeksInTop10": 2,
        "maturityRating": "TV-G",
        "weeklyHoursViewed": 3800000,
        "weeklyViews": 0,
        "runtime": "0",
        "runtime_second": 0,
        "runtime_hmm": "0:00",
        "bigImage": "https://dnm.nflximg.net/api/v6/E8vDc_W8CLv7-yMQu8KMEC7Rrr8/AAAABd8rpOZnffXS-mTo7qJ78O_s33DR37qa3rJXb75BNf2VOiV3ZqlxOju4gcD1HQUFNVa2SD4A7ER1ht7CVqZYQAE1X7q4fkuiSUPI.jpg?r=d6b",
        "weekEndDate": "2022-11-20",
        "videoId": "81435416",
        "category": "NONENGLISH_MOVIES",
        "title": "The Claus Family 2",
        "shortSynopsis": "Santa's one job? Deliver presents. But as Jules takes the reins from his Grandpa Noël, he receives a young girl's letter with a special holiday wish.",
        "releaseYear": "2021",
        "groupfile": "films-non-english"
    },
    {
        "weeklyRank": 8,
        "cumulativeWeeksInTop10": 2,
        "maturityRating": "TV-MA",
        "weeklyHoursViewed": 3410000,
        "weeklyViews": 0,
        "runtime": "0",
        "runtime_second": 0,
        "runtime_hmm": "0:00",
        "bigImage": "https://dnm.nflximg.net/api/v6/E8vDc_W8CLv7-yMQu8KMEC7Rrr8/AAAABR8-Hi-BBE7Fa7YRv-hAf_DTKn2lWDuShie-arps3T9BD6df-mew5uOi7VG4jDYYjvxv1FiV1Z8SkJGu-FTgyacN04ItzW2v1_WM.jpg?r=a97",
        "weekEndDate": "2022-11-20",
        "videoId": "81334952",
        "category": "NONENGLISH_MOVIES",
        "title": "Don't Leave",
        "shortSynopsis": "Semih's girlfriend suddenly breaks up with him. In search of answers about their relationship, he must soon confront what he had long ignored.",
        "releaseYear": "2022",
        "groupfile": "films-non-english"
    },
    {
        "weeklyRank": 9,
        "cumulativeWeeksInTop10": 4,
        "maturityRating": "TV-14",
        "weeklyHoursViewed": 3230000,
        "weeklyViews": 0,
        "runtime": "0",
        "runtime_second": 0,
        "runtime_hmm": "0:00",
        "bigImage": "https://dnm.nflximg.net/api/v6/E8vDc_W8CLv7-yMQu8KMEC7Rrr8/AAAABYE2KQVFyduFFQ0gCf6Q0hyJJeCPuSH1YzULEaFXRr7rSDltHk-DyS4mFyAngD_vmULmfaVvLDYA490JnVJYF0Vh3jyOGV10F_li.jpg?r=793",
        "weekEndDate": "2022-11-20",
        "videoId": "80242820",
        "category": "NONENGLISH_MOVIES",
        "title": "The Chalk Line",
        "shortSynopsis": "After a couple finds a traumatized child of unknown origins, wife Paula must decipher the girl's strange behaviors to unlock her identity and dark past.",
        "releaseYear": "2022",
        "groupfile": "films-non-english"
    },
    {
        "weeklyRank": 10,
        "cumulativeWeeksInTop10": 3,
        "maturityRating": "TV-MA",
        "weeklyHoursViewed": 2620000,
        "weeklyViews": 0,
        "runtime": "0",
        "runtime_second": 0,
        "runtime_hmm": "0:00",
        "bigImage": "https://dnm.nflximg.net/api/v6/E8vDc_W8CLv7-yMQu8KMEC7Rrr8/AAAABRJVT9nFVEDEQdqakkE5HHagIC4uG7ggP0aqV1yRhM-9vkeWsQUES_KqgNrROvRevsHZyM-RYG_IHCPR13m2_yvdg4RXXr66XRFE.jpg?r=5f0",
        "weekEndDate": "2022-11-20",
        "videoId": "81488967",
        "category": "NONENGLISH_MOVIES",
        "title": "The Takeover",
        "shortSynopsis": "Framed for murder after uncovering a privacy scandal, an ethical hacker must evade the police while trying to track down the criminals blackmailing her.",
        "releaseYear": "2022",
        "groupfile": "films-non-english"
    },
    {
        "weeklyRank": 1,
        "cumulativeWeeksInTop10": 6,
        "maturityRating": "TV-MA",
        "weeklyHoursViewed": 84310000,
        "weeklyViews": 0,
        "runtime": "0",
        "runtime_second": 0,
        "runtime_hmm": "0:00",
        "bigImage": "https://dnm.nflximg.net/api/v6/E8vDc_W8CLv7-yMQu8KMEC7Rrr8/AAAABUt3llP11tT0HUn7w4AwMEcgaD4Tflrv1FszJpkwwlgdTq9OAWLpowOGgyIrx3VdYWaRFQ_RZSDEuEYx2OdNZT1BUQ7znSCHhl7W.jpg?r=244",
        "weekEndDate": "2022-11-20",
        "videoId": "81318159",
        "category": "ENGLISH_SERIES",
        "title": "The Crown: Season 5",
        "shortSynopsis": "Diana and Charles wage a media war. The monarchy's role is up for debate. Welcome to the '90s — and Queen Elizabeth II's biggest challenge to date.",
        "releaseYear": "2022",
        "groupfile": "tv"
    },
    {
        "weeklyRank": 2,
        "cumulativeWeeksInTop10": 5,
        "maturityRating": "TV-MA",
        "weeklyHoursViewed": 79270000,
        "weeklyViews": 0,
        "runtime": "0",
        "runtime_second": 0,
        "runtime_hmm": "0:00",
        "bigImage": "https://dnm.nflximg.net/api/v6/E8vDc_W8CLv7-yMQu8KMEC7Rrr8/AAAABYONgqsOESv26FLPGx9bbi33EF3xQUW90_hJX0IILAleMVoXfXDWwilcV2ZYLyEFcnlhaHGqz1pPqvlNlR6gM9--03R1vZQ3vafZ.jpg?r=aaa",
        "weekEndDate": "2022-11-20",
        "videoId": "80234387",
        "category": "ENGLISH_SERIES",
        "title": "1899: Season 1",
        "shortSynopsis": "When mysterious events change the course of an immigrant ship headed for New York in 1899, a mind-bending riddle unfolds for its bewildered passengers.",
        "releaseYear": "2022",
        "groupfile": "tv"
    },
    {
        "weeklyRank": 3,
        "cumulativeWeeksInTop10": 9,
        "maturityRating": "TV-14",
        "weeklyHoursViewed": 35730000,
        "weeklyViews": 0,
        "runtime": "0",
        "runtime_second": 0,
        "runtime_hmm": "0:00",
        "bigImage": "https://dnm.nflximg.net/api/v6/E8vDc_W8CLv7-yMQu8KMEC7Rrr8/AAAABe65OyxNXDI2JB8caRSi6gx2tV2l45iz73uhnTqp4Xsho8sd8QhpKMxoN6UTNXhAVdbgU8dgc_n2rYTbxq82Wi2YLDN9reXr8Stn.jpg?r=049",
        "weekEndDate": "2022-11-20",
        "videoId": "81509345",
        "category": "ENGLISH_SERIES",
        "title": "Manifest: Season 4",
        "shortSynopsis": "Amid loss and misfortune, the Stone family and the Flight 828 passengers search for the true meaning behind their Callings as ominous signs linger.",
        "releaseYear": "2022",
        "groupfile": "tv"
    },
    {
        "weeklyRank": 4,
        "cumulativeWeeksInTop10": 4,
        "maturityRating": "TV-MA",
        "weeklyHoursViewed": 30300000,
        "weeklyViews": 0,
        "runtime": "0",
        "runtime_second": 0,
        "runtime_hmm": "0:00",
        "bigImage": "https://dnm.nflximg.net/api/v6/E8vDc_W8CLv7-yMQu8KMEC7Rrr8/AAAABcogZS78X2ukISbfCNw46FImhwEkub7ta5NuqYJ6NxJOI9w9szU-FA_1wQEluoqBj_LRh2ilqO7ZwBvjviNlbAZnbyqRwRhX0eNI.jpg?r=bd8",
        "weekEndDate": "2022-11-20",
        "videoId": "81144333",
        "category": "ENGLISH_SERIES",
        "title": "Dead to Me: Season 3",
        "shortSynopsis": "A hit-and-run started it all for Jen and Judy. Now another shocking crash alters the future of their ride-or-die friendship. All roads have led to this.",
        "releaseYear": "2022",
        "groupfile": "tv"
    },
    {
        "weeklyRank": 5,
        "cumulativeWeeksInTop10": 3,
        "maturityRating": "TV-MA",
        "weeklyHoursViewed": 27740000,
        "weeklyViews": 0,
        "runtime": "0",
        "runtime_second": 0,
        "runtime_hmm": "0:00",
        "bigImage": "https://dnm.nflximg.net/api/v6/E8vDc_W8CLv7-yMQu8KMEC7Rrr8/AAAABY19rIQv5pxP1bkR3SMNaCYblQfF5sAU-gwSzaTiM2YSwM0tPHJyWOq87U7EsuZacUYNjUpOGboQpLO7bwybqArTLohAJZxgRz2I.jpg?r=985",
        "weekEndDate": "2022-11-20",
        "videoId": "81160056",
        "category": "ENGLISH_SERIES",
        "title": "Warrior Nun: Season 2",
        "shortSynopsis": "Alongside new allies, Ava and the sisters of the Order band together and set out to take down a false prophet hell-bent on world domination.",
        "releaseYear": "2022",
        "groupfile": "tv"
    },
    {
        "weeklyRank": 6,
        "cumulativeWeeksInTop10": 25,
        "maturityRating": "TV-14",
        "weeklyHoursViewed": 25940000,
        "weeklyViews": 0,
        "runtime": "0",
        "runtime_second": 0,
        "runtime_hmm": "0:00",
        "bigImage": "https://dnm.nflximg.net/api/v6/E8vDc_W8CLv7-yMQu8KMEC7Rrr8/AAAABY_PbE7sc3BsC_It96DwhcXSI2nf0ErDgUoq1zR-Si-pnJrZcLb8zJOHJTifyhiY4kZNfRTYDCBGc1ldrP-JcfyCXAaK0syQ_9BK.jpg?r=066",
        "weekEndDate": "2022-11-20",
        "videoId": "81015482",
        "category": "ENGLISH_SERIES",
        "title": "Manifest: Season 1",
        "shortSynopsis": "When a plane mysteriously lands years after takeoff, the people onboard return to a world that has moved on without them and face strange new realities.",
        "releaseYear": "2018",
        "groupfile": "tv"
    },
    {
        "weeklyRank": 7,
        "cumulativeWeeksInTop10": 1,
        "maturityRating": "TV-14",
        "weeklyHoursViewed": 24620000,
        "weeklyViews": 0,
        "runtime": "0",
        "runtime_second": 0,
        "runtime_hmm": "0:00",
        "bigImage": "https://dnm.nflximg.net/api/v6/E8vDc_W8CLv7-yMQu8KMEC7Rrr8/AAAABUG6y32Aop4E3ERh2Zw3goY4xR_x5xOU5fiYBOQdfhbjVlB0Cm4j1lCii2tHzdv0XcJpjqPhh0ai3n9IjedpjuJAdoyRoZeBf2as.jpg?r=374",
        "weekEndDate": "2022-11-20",
        "videoId": "81222573",
        "category": "ENGLISH_SERIES",
        "title": "Ancient Apocalypse: Season 1",
        "shortSynopsis": "Journalist Graham Hancock travels the globe hunting for evidence of mysterious, lost civilizations dating back to the last Ice Age.",
        "releaseYear": "2022",
        "groupfile": "tv"
    },
    {
        "weeklyRank": 8,
        "cumulativeWeeksInTop10": 1,
        "maturityRating": "TV-MA",
        "weeklyHoursViewed": 20100000,
        "weeklyViews": 0,
        "runtime": "0",
        "runtime_second": 0,
        "runtime_hmm": "0:00",
        "bigImage": "https://dnm.nflximg.net/api/v6/E8vDc_W8CLv7-yMQu8KMEC7Rrr8/AAAABfjMRDDf_9RjReppnRoDKqYSdJ5n7S-udHTmKih3UUykpgGpzMn13Jalua30bTNoR4Xd0LC1DHDmTO5NRNYhsipCci4XumGgYwdg.jpg?r=b42",
        "weekEndDate": "2022-11-20",
        "videoId": "80998762",
        "category": "ENGLISH_SERIES",
        "title": "Warrior Nun: Season 1",
        "shortSynopsis": "After waking up in a morgue, an orphaned teen discovers she now possesses superpowers as the chosen Halo-Bearer for a secret sect of demon-hunting nuns.",
        "releaseYear": "2020",
        "groupfile": "tv"
    },
    {
        "weeklyRank": 9,
        "cumulativeWeeksInTop10": 5,
        "maturityRating": "TV-MA",
        "weeklyHoursViewed": 19880000,
        "weeklyViews": 0,
        "runtime": "0",
        "runtime_second": 0,
        "runtime_hmm": "0:00",
        "bigImage": "https://dnm.nflximg.net/api/v6/E8vDc_W8CLv7-yMQu8KMEC7Rrr8/AAAABQycUFcA3t91Cc0iTMz-knyPCiefzpQ5OmLIA0uwCKLT4tRAVP_Bxlq1Gk5DvpgSAexYkFmFBaSC_eIEAhxqkYuMZD97WDfNVLR-.jpg?r=8f9",
        "weekEndDate": "2022-11-20",
        "videoId": "81127414",
        "category": "ENGLISH_SERIES",
        "title": "From Scratch: Limited Series",
        "shortSynopsis": "An artist finds romance with a chef in Italy and embarks on a life-changing journey of love, loss, resilience and hope across cultures and continents.",
        "releaseYear": "2022",
        "groupfile": "tv"
    },
    {
        "weeklyRank": 10,
        "cumulativeWeeksInTop10": 7,
        "maturityRating": "TV-MA",
        "weeklyHoursViewed": 19310000,
        "weeklyViews": 0,
        "runtime": "0",
        "runtime_second": 0,
        "runtime_hmm": "0:00",
        "bigImage": "https://dnm.nflximg.net/api/v6/E8vDc_W8CLv7-yMQu8KMEC7Rrr8/AAAABR4rOKqfCxw77TFfEF6E3lrzydutjHoobpsiuoRFlHOGQL_BbxA3vuafXux9GgZvWyOKqnX1pPZ0RZ8JXpkx4E3dCrxg9qR47nPd.jpg?r=fd0",
        "weekEndDate": "2022-11-20",
        "videoId": "81266274",
        "category": "ENGLISH_SERIES",
        "title": "Love Is Blind: Season 3",
        "shortSynopsis": "Riding an emotional roller coaster from the pods to the altar, a new group of singles must decide if they dare to propose to someone they've never seen.",
        "releaseYear": "2022",
        "groupfile": "tv"
    },
    {
        "weeklyRank": 1,
        "cumulativeWeeksInTop10": 12,
        "maturityRating": "13+",
        "weeklyHoursViewed": 39960000,
        "weeklyViews": 0,
        "runtime": "0",
        "runtime_second": 0,
        "runtime_hmm": "0:00",
        "bigImage": "https://dnm.nflximg.net/api/v6/E8vDc_W8CLv7-yMQu8KMEC7Rrr8/AAAABW-pbCIva__oIESbE4he9OMlvC63-aYfJxUvmijJvToTT2CmuBu3L2s-N8ZFmeqbw50wSY9P9bc9q2xs0MWDHcUTD1k4GGyVbOXP.jpg?r=d8a",
        "weekEndDate": "2022-11-20",
        "videoId": "81609359",
        "category": "NONENGLISH_SERIES",
        "title": "Til Money Do Us Part: Season 1",
        "shortSynopsis": "When a rich and glamorous sales manager is injured in a car accident, her vengeance toward the humble man driving the other car slowly gives way to love.",
        "releaseYear": "2022",
        "groupfile": "tv-non-english"
    },
    {
        "weeklyRank": 2,
        "cumulativeWeeksInTop10": 4,
        "maturityRating": "TV-MA",
        "weeklyHoursViewed": 36870000,
        "weeklyViews": 0,
        "runtime": "0",
        "runtime_second": 0,
        "runtime_hmm": "0:00",
        "bigImage": "https://dnm.nflximg.net/api/v6/E8vDc_W8CLv7-yMQu8KMEC7Rrr8/AAAABYKbIBFv77nl3bZLkwMOYIfuOWtU47aUuUmivGF4n9fH9gAUSka96u9bEFrHdX4HNf_wJtZ1kCegfaLWx0x9fAbCfCMXNhCDJvSc.jpg?r=b5a",
        "weekEndDate": "2022-11-20",
        "videoId": "81478034",
        "category": "NONENGLISH_SERIES",
        "title": "Elite: Season 6",
        "shortSynopsis": "Everybody's looking for something this year at Las Encinas, whether it's love, revenge or millions of followers. But will they all make it out alive?",
        "releaseYear": "2022",
        "groupfile": "tv-non-english"
    },
    {
        "weeklyRank": 3,
        "cumulativeWeeksInTop10": 8,
        "maturityRating": "TV-14",
        "weeklyHoursViewed": 15620000,
        "weeklyViews": 0,
        "runtime": "0",
        "runtime_second": 0,
        "runtime_hmm": "0:00",
        "bigImage": "https://dnm.nflximg.net/api/v6/E8vDc_W8CLv7-yMQu8KMEC7Rrr8/AAAABW1HLDZkOOBKK-_aL2FKefAGx34yjevSk7LSb-f7DtU9wCbBlVHEEKUYE56tqSI4qJJDo8VLKbVZ_WEjJgUGQ3DVsnoOCQ0X06QG.jpg?r=13c",
        "weekEndDate": "2022-11-20",
        "videoId": "81610894",
        "category": "NONENGLISH_SERIES",
        "title": "Under the Queen's Umbrella: Limited Series",
        "shortSynopsis": "A spirited queen tries to rein in her rowdy sons in order to make one of them the next king of Joseon, while her competitors vie to snatch the throne.",
        "releaseYear": "2022",
        "groupfile": "tv-non-english"
    },
    {
        "weeklyRank": 4,
        "cumulativeWeeksInTop10": 11,
        "maturityRating": "TV-MA",
        "weeklyHoursViewed": 8590000,
        "weeklyViews": 0,
        "runtime": "0",
        "runtime_second": 0,
        "runtime_hmm": "0:00",
        "bigImage": "https://dnm.nflximg.net/api/v6/E8vDc_W8CLv7-yMQu8KMEC7Rrr8/AAAABT1DaD_JR9rLSc72OVS-OF5TELxXtG9NvIr9Bh-U8fpSSsNN9uHQRDVe3dWM8sIZHOHP_uQeRJix1nf60QwIDUwKJDjyDoOprirv.jpg?r=23d",
        "weekEndDate": "2022-11-20",
        "videoId": "81610896",
        "category": "NONENGLISH_SERIES",
        "title": "Little Women: Limited Series",
        "shortSynopsis": "Three sisters, who only have each other and never enough money, get entangled in a conspiracy involving the rich and powerful.",
        "releaseYear": "2022",
        "groupfile": "tv-non-english"
    },
    {
        "weeklyRank": 5,
        "cumulativeWeeksInTop10": 10,
        "maturityRating": "12",
        "weeklyHoursViewed": 7940000,
        "weeklyViews": 0,
        "runtime": "0",
        "runtime_second": 0,
        "runtime_hmm": "0:00",
        "bigImage": "https://dnm.nflximg.net/api/v6/E8vDc_W8CLv7-yMQu8KMEC7Rrr8/AAAABWq3V8JN4OVTJ997Ceaq61Fz2k8myalk1gJ_oNoHVVubO2xMsarRig_PVLMlnkpNKJlx7bVtBjtTgIZzSz7iGE0t7E2FdhpkjjVb.jpg?r=f03",
        "weekEndDate": "2022-11-20",
        "videoId": "80059313",
        "category": "NONENGLISH_SERIES",
        "title": "Chiquititas: Season 1",
        "shortSynopsis": "A devoted young woman helps a group of orphans through the trials of growing up as they live like a family in a manor called the Corner of Light.",
        "releaseYear": "2013",
        "groupfile": "tv-non-english"
    },
    {
        "weeklyRank": 6,
        "cumulativeWeeksInTop10": 28,
        "maturityRating": "16+",
        "weeklyHoursViewed": 6850000,
        "weeklyViews": 0,
        "runtime": "0",
        "runtime_second": 0,
        "runtime_hmm": "0:00",
        "bigImage": "https://dnm.nflximg.net/api/v6/E8vDc_W8CLv7-yMQu8KMEC7Rrr8/AAAABffJVmOY2NV4QFQLdLvRDYydtvmNgo5vlT3HHQNNdRTL82FOUmx6MU8c2dDcotAzFaqYrWo_hLTSZAln8MDewZsdK6QX3y3TGACd.jpg?r=504",
        "weekEndDate": "2022-11-20",
        "videoId": "81396407",
        "category": "NONENGLISH_SERIES",
        "title": "Café con aroma de mujer: Season 1",
        "shortSynopsis": "A remake of the 1994 classic telenovela, this is the love story between Gaviota, a coffee picker, and Sebastián, the scion of coffee aristocracy.",
        "releaseYear": "2021",
        "groupfile": "tv-non-english"
    },
    {
        "weeklyRank": 7,
        "cumulativeWeeksInTop10": 21,
        "maturityRating": "TV-14",
        "weeklyHoursViewed": 6780000,
        "weeklyViews": 0,
        "runtime": "0",
        "runtime_second": 0,
        "runtime_hmm": "0:00",
        "bigImage": "https://dnm.nflximg.net/api/v6/E8vDc_W8CLv7-yMQu8KMEC7Rrr8/AAAABaXYKPZSh2KjA8kwQJDdrQ6wyrrLIhYorgW3Aq4ph9OUyjsFoHeZPgq2387Y164ggn5VzjM7KgRkYwLNYoHc1vrixfbGFktZKQI8.jpg?r=049",
        "weekEndDate": "2022-11-20",
        "videoId": "81518992",
        "category": "NONENGLISH_SERIES",
        "title": "Extraordinary Attorney Woo: Season 1",
        "shortSynopsis": "Brilliant attorney Woo Young-woo tackles challenges in the courtroom and beyond as a newbie at a top law firm and a woman on the autism spectrum.",
        "releaseYear": "2022",
        "groupfile": "tv-non-english"
    },
    {
        "weeklyRank": 8,
        "cumulativeWeeksInTop10": 8,
        "maturityRating": "TV-MA",
        "weeklyHoursViewed": 5760000,
        "weeklyViews": 0,
        "runtime": "0",
        "runtime_second": 0,
        "runtime_hmm": "0:00",
        "bigImage": "https://dnm.nflximg.net/api/v6/E8vDc_W8CLv7-yMQu8KMEC7Rrr8/AAAABTrbUQ3njkOq3ckdbt2JLeEHLZFBkSufdBBaCyXlF2M6HVHR1XFLr3osdIsr7bRPu7M9ZhPNOsAkU_xTtdKfVQ-iyu6LT9e9tR5B.jpg?r=909",
        "weekEndDate": "2022-11-20",
        "videoId": "80035484",
        "category": "NONENGLISH_SERIES",
        "title": "Pablo Escobar, el patrón del mal: Season 1",
        "shortSynopsis": "An errant and rebellious boy chooses a life of crime, which escalates, catapulting him into the role of the world's most notorious drug lord.",
        "releaseYear": "2012",
        "groupfile": "tv-non-english"
    },
    {
        "weeklyRank": 9,
        "cumulativeWeeksInTop10": 1,
        "maturityRating": "TV-MA",
        "weeklyHoursViewed": 5420000,
        "weeklyViews": 0,
        "runtime": "0",
        "runtime_second": 0,
        "runtime_hmm": "0:00",
        "bigImage": "https://dnm.nflximg.net/api/v6/E8vDc_W8CLv7-yMQu8KMEC7Rrr8/AAAABf3AUd65DGUauWNawi7p0TYGwzGdYwJrp9i2wB7tlysAwt5GzgPD5V6h7N51CNWZsvaAEzwiXJ-bNhVYGFkqw7GP6xsQIGqxdA0b.jpg?r=94f",
        "weekEndDate": "2022-11-20",
        "videoId": "81565023",
        "category": "NONENGLISH_SERIES",
        "title": "Love Never Lies: Destination Sardinia: Season 1",
        "shortSynopsis": "A new group of supposedly solid couples put their relationships to the test. In their pursuit of love and money, will the truth hurt or heal?",
        "releaseYear": "2022",
        "groupfile": "tv-non-english"
    },
    {
        "weeklyRank": 10,
        "cumulativeWeeksInTop10": 4,
        "maturityRating": "TV-MA",
        "weeklyHoursViewed": 5400000,
        "weeklyViews": 0,
        "runtime": "0",
        "runtime_second": 0,
        "runtime_hmm": "0:00",
        "bigImage": "https://dnm.nflximg.net/api/v6/E8vDc_W8CLv7-yMQu8KMEC7Rrr8/AAAABfysIU_sDpLXAFYrVC3q8Ww-k3hUZwleSmmW9Hu3fF8DJ9D5kdRKaZlwic2wP7LllsuqJ2oggUqY3R93IvHBYZsb6jo0rXn2Gx2o.jpg?r=b5f",
        "weekEndDate": "2022-11-20",
        "videoId": "81462122",
        "category": "NONENGLISH_SERIES",
        "title": "Dubai Bling: Season 1",
        "shortSynopsis": "Step off the private jet and into a high-flying social circle in Dubai, where lavish parties, stunning skylines and jaw-dropping fashion are the norm.",
        "releaseYear": "2022",
        "groupfile": "tv-non-english"
    }
]